{
  "db_name": "PostgreSQL",
  "query": "SELECT kind as \"kind: IndexKind\", SUM(records)::bigint as \"records!\" FROM indexes\n              JOIN segments ON index_id = indexes.id\n              WHERE shard_id = $1\n              GROUP BY kind",
  "describe": {
    "columns": [
      {
        "ordinal": 0,
        "name": "kind: IndexKind",
        "type_info": {
          "Custom": {
            "name": "index_kind",
            "kind": {
              "Enum": [
                "text",
                "paragraph",
                "vector",
                "relation"
              ]
            }
          }
        }
      },
      {
        "ordinal": 1,
        "name": "records!",
        "type_info": "Int8"
      }
    ],
    "parameters": {
      "Left": [
        "Uuid"
      ]
    },
    "nullable": [
      false,
      null
    ]
  },
  "hash": "ef25d1b091b8edce55dcd7f0a2f528537cd9329ab7297b81ace0aba8c0e1bb0e"
}
