{
  "db_name": "PostgreSQL",
  "query": "SELECT * FROM segments WHERE index_id = ANY($1) AND delete_at IS NULL",
  "describe": {
    "columns": [
      {
        "ordinal": 0,
        "name": "id",
        "type_info": "Int8"
      },
      {
        "ordinal": 1,
        "name": "index_id",
        "type_info": "Int8"
      },
      {
        "ordinal": 2,
        "name": "seq",
        "type_info": "Int8"
      },
      {
        "ordinal": 3,
        "name": "records",
        "type_info": "Int8"
      },
      {
        "ordinal": 4,
        "name": "size_bytes",
        "type_info": "Int8"
      },
      {
        "ordinal": 5,
        "name": "merge_job_id",
        "type_info": "Int8"
      },
      {
        "ordinal": 6,
        "name": "index_metadata",
        "type_info": "Json"
      },
      {
        "ordinal": 7,
        "name": "delete_at",
        "type_info": "Timestamp"
      }
    ],
    "parameters": {
      "Left": [
        "Int8Array"
      ]
    },
    "nullable": [
      false,
      false,
      false,
      false,
      true,
      true,
      false,
      true
    ]
  },
  "hash": "917732a56ee04bf3a6e127319dda8225210869c82f9828d878162394dba4e078"
}
