{
  "db_name": "PostgreSQL",
  "query": "DELETE FROM merge_jobs WHERE running_at < NOW() - INTERVAL '1 minute' AND retries >= 4 RETURNING *",
  "describe": {
    "columns": [
      {
        "ordinal": 0,
        "name": "id",
        "type_info": "Int8"
      },
      {
        "ordinal": 1,
        "name": "retries",
        "type_info": "Int2"
      },
      {
        "ordinal": 2,
        "name": "seq",
        "type_info": "Int8"
      },
      {
        "ordinal": 3,
        "name": "enqueued_at",
        "type_info": "Timestamp"
      },
      {
        "ordinal": 4,
        "name": "started_at",
        "type_info": "Timestamp"
      },
      {
        "ordinal": 5,
        "name": "running_at",
        "type_info": "Timestamp"
      }
    ],
    "parameters": {
      "Left": []
    },
    "nullable": [
      false,
      false,
      false,
      false,
      true,
      true
    ]
  },
  "hash": "5e1f1e5904356fa8b462a0fe3424ea9f612b6c4b338af9b431a2b121b4799f0c"
}
