{
  "db_name": "PostgreSQL",
  "query": "SELECT * FROM shards WHERE id = $1 AND deleted_at IS NULL",
  "describe": {
    "columns": [
      {
        "ordinal": 0,
        "name": "id",
        "type_info": "Uuid"
      },
      {
        "ordinal": 1,
        "name": "kbid",
        "type_info": "Uuid"
      },
      {
        "ordinal": 2,
        "name": "deleted_at",
        "type_info": "Timestamp"
      }
    ],
    "parameters": {
      "Left": [
        "Uuid"
      ]
    },
    "nullable": [
      false,
      false,
      true
    ]
  },
  "hash": "ef56d5fefc5774040d1ee397beadb475f6af02768c22f0e583c74062e2e821ce"
}
